LICENSE
README.md
uncertainAPI/__init__.py
uncertainAPI/main.py
uncertainAPI/py.typed
uncertainapi-0.1.2.dev0.dist-info/METADATA
uncertainapi-0.1.2.dev0.dist-info/WHEEL
uncertainapi-0.1.2.dev0.dist-info/licenses/LICENSE
uncertainapi-0.1.2.dev0.dist-info/RECORD
