Metadata-Version: 2.4
Name: uncertainAPI
Version: 0.1.2.dev0
Summary: A Python package for uncertainAPI
License-Expression: MIT
License-File: LICENSE
Keywords: uncertainAPI,API,Python,AI,Python Framework
Author: Iyanuoluwa Adebayo
Author-email: adebayo@uncertainapi.com
Requires-Python: >= 3.8
Classifier: Development Status :: 1 - Planning
Classifier: Intended Audience :: Developers
Classifier: Programming Language :: Python :: 3
Classifier: Programming Language :: Python :: 3.8
Classifier: Programming Language :: Python :: 3.9
Classifier: Programming Language :: Python :: 3.10
Classifier: Programming Language :: Python :: 3.11
Classifier: Programming Language :: Python :: 3.12
Classifier: License :: OSI Approved :: MIT License
Classifier: Topic :: Software Development :: Libraries
Classifier: Topic :: Software Development :: Libraries :: Application Frameworks
Classifier: Topic :: Software Development :: Libraries :: Python Modules
Classifier: Topic :: Utilities
Provides-Extra: dev
Requires-Dist: black (>=23.0) ; extra == "dev"
Requires-Dist: mypy (>=1.0) ; extra == "dev"
Requires-Dist: pytest (>=7.0) ; extra == "dev"
Requires-Dist: pytest-cov (>=4.0) ; extra == "dev"
Requires-Dist: ruff (>=0.1.0) ; extra == "dev"
Project-URL: Homepage, https://uncertainapi.com/
Project-URL: Repository, https://github.com/Lux-speed-labs/uncertainAPI
